<?xml version="1.0" encoding="UTF-8" standalone="yes"?>
<w:numbering xmlns:wpc="http://schemas.microsoft.com/office/word/2010/wordprocessingCanvas" xmlns:cx="http://schemas.microsoft.com/office/drawing/2014/chartex" xmlns:cx1="http://schemas.microsoft.com/office/drawing/2015/9/8/chartex" xmlns:cx2="http://schemas.microsoft.com/office/drawing/2015/10/21/chartex" xmlns:cx3="http://schemas.microsoft.com/office/drawing/2016/5/9/chartex" xmlns:cx4="http://schemas.microsoft.com/office/drawing/2016/5/10/chartex" xmlns:cx5="http://schemas.microsoft.com/office/drawing/2016/5/11/chartex" xmlns:cx6="http://schemas.microsoft.com/office/drawing/2016/5/12/chartex" xmlns:cx7="http://schemas.microsoft.com/office/drawing/2016/5/13/chartex" xmlns:cx8="http://schemas.microsoft.com/office/drawing/2016/5/14/chartex" xmlns:mc="http://schemas.openxmlformats.org/markup-compatibility/2006" xmlns:aink="http://schemas.microsoft.com/office/drawing/2016/ink" xmlns:am3d="http://schemas.microsoft.com/office/drawing/2017/model3d" xmlns:o="urn:schemas-microsoft-com:office:office" xmlns:oel="http://schemas.microsoft.com/office/2019/extlst" xmlns:r="http://schemas.openxmlformats.org/officeDocument/2006/relationships" xmlns:m="http://schemas.openxmlformats.org/officeDocument/2006/math" xmlns:v="urn:schemas-microsoft-com:vml" xmlns:wp14="http://schemas.microsoft.com/office/word/2010/wordprocessingDrawing" xmlns:wp="http://schemas.openxmlformats.org/drawingml/2006/wordprocessingDrawing" xmlns:w10="urn:schemas-microsoft-com:office:word" xmlns:w="http://schemas.openxmlformats.org/wordprocessingml/2006/main" xmlns:w14="http://schemas.microsoft.com/office/word/2010/wordml" xmlns:w15="http://schemas.microsoft.com/office/word/2012/wordml" xmlns:w16cex="http://schemas.microsoft.com/office/word/2018/wordml/cex" xmlns:w16cid="http://schemas.microsoft.com/office/word/2016/wordml/cid" xmlns:w16="http://schemas.microsoft.com/office/word/2018/wordml" xmlns:w16du="http://schemas.microsoft.com/office/word/2023/wordml/word16du" xmlns:w16sdtdh="http://schemas.microsoft.com/office/word/2020/wordml/sdtdatahash" xmlns:w16sdtfl="http://schemas.microsoft.com/office/word/2024/wordml/sdtformatlock" xmlns:w16se="http://schemas.microsoft.com/office/word/2015/wordml/symex" xmlns:wpg="http://schemas.microsoft.com/office/word/2010/wordprocessingGroup" xmlns:wpi="http://schemas.microsoft.com/office/word/2010/wordprocessingInk" xmlns:wne="http://schemas.microsoft.com/office/word/2006/wordml" xmlns:wps="http://schemas.microsoft.com/office/word/2010/wordprocessingShape" mc:Ignorable="w14 w15 w16se w16cid w16 w16cex w16sdtdh w16sdtfl w16du wp14"><w:abstractNum w:abstractNumId="0" w15:restartNumberingAfterBreak="0"><w:nsid w:val="14D3234F"/><w:multiLevelType w:val="hybridMultilevel"/><w:tmpl w:val="4F76F5D8"/><w:lvl w:ilvl="0" w:tplc="1D7EED3C"><w:numFmt w:val="bullet"/><w:lvlText w:val="•"/><w:lvlJc w:val="left"/><w:pPr><w:ind w:left="861" w:hanging="500"/></w:pPr><w:rPr><w:rFonts w:ascii="Times New Roman" w:eastAsia="Times New Roman" w:hAnsi="Times New Roman" w:cs="Times New Roman" w:hint="default"/><w:b w:val="0"/><w:bCs w:val="0"/><w:i w:val="0"/><w:iCs w:val="0"/><w:spacing w:val="0"/><w:w w:val="100"/><w:sz w:val="38"/><w:szCs w:val="38"/><w:lang w:val="en-US" w:eastAsia="en-US" w:bidi="ar-SA"/></w:rPr></w:lvl><w:lvl w:ilvl="1" w:tplc="CBCAA45C"><w:numFmt w:val="bullet"/><w:lvlText w:val="•"/><w:lvlJc w:val="left"/><w:pPr><w:ind w:left="1752" w:hanging="500"/></w:pPr><w:rPr><w:rFonts w:hint="default"/><w:lang w:val="en-US" w:eastAsia="en-US" w:bidi="ar-SA"/></w:rPr></w:lvl><w:lvl w:ilvl="2" w:tplc="CC58005A"><w:numFmt w:val="bullet"/><w:lvlText w:val="•"/><w:lvlJc w:val="left"/><w:pPr><w:ind w:left="2644" w:hanging="500"/></w:pPr><w:rPr><w:rFonts w:hint="default"/><w:lang w:val="en-US" w:eastAsia="en-US" w:bidi="ar-SA"/></w:rPr></w:lvl><w:lvl w:ilvl="3" w:tplc="C4AEC7E4"><w:numFmt w:val="bullet"/><w:lvlText w:val="•"/><w:lvlJc w:val="left"/><w:pPr><w:ind w:left="3536" w:hanging="500"/></w:pPr><w:rPr><w:rFonts w:hint="default"/><w:lang w:val="en-US" w:eastAsia="en-US" w:bidi="ar-SA"/></w:rPr></w:lvl><w:lvl w:ilvl="4" w:tplc="1F88EB2A"><w:numFmt w:val="bullet"/><w:lvlText w:val="•"/><w:lvlJc w:val="left"/><w:pPr><w:ind w:left="4428" w:hanging="500"/></w:pPr><w:rPr><w:rFonts w:hint="default"/><w:lang w:val="en-US" w:eastAsia="en-US" w:bidi="ar-SA"/></w:rPr></w:lvl><w:lvl w:ilvl="5" w:tplc="6B3EA5F0"><w:numFmt w:val="bullet"/><w:lvlText w:val="•"/><w:lvlJc w:val="left"/><w:pPr><w:ind w:left="5320" w:hanging="500"/></w:pPr><w:rPr><w:rFonts w:hint="default"/><w:lang w:val="en-US" w:eastAsia="en-US" w:bidi="ar-SA"/></w:rPr></w:lvl><w:lvl w:ilvl="6" w:tplc="625CEFB8"><w:numFmt w:val="bullet"/><w:lvlText w:val="•"/><w:lvlJc w:val="left"/><w:pPr><w:ind w:left="6212" w:hanging="500"/></w:pPr><w:rPr><w:rFonts w:hint="default"/><w:lang w:val="en-US" w:eastAsia="en-US" w:bidi="ar-SA"/></w:rPr></w:lvl><w:lvl w:ilvl="7" w:tplc="1E7CD908"><w:numFmt w:val="bullet"/><w:lvlText w:val="•"/><w:lvlJc w:val="left"/><w:pPr><w:ind w:left="7104" w:hanging="500"/></w:pPr><w:rPr><w:rFonts w:hint="default"/><w:lang w:val="en-US" w:eastAsia="en-US" w:bidi="ar-SA"/></w:rPr></w:lvl><w:lvl w:ilvl="8" w:tplc="AC141F1E"><w:numFmt w:val="bullet"/><w:lvlText w:val="•"/><w:lvlJc w:val="left"/><w:pPr><w:ind w:left="7996" w:hanging="500"/></w:pPr><w:rPr><w:rFonts w:hint="default"/><w:lang w:val="en-US" w:eastAsia="en-US" w:bidi="ar-SA"/></w:rPr></w:lvl></w:abstractNum><w:abstractNum w:abstractNumId="1" w15:restartNumberingAfterBreak="0"><w:nsid w:val="483B3402"/><w:multiLevelType w:val="hybridMultilevel"/><w:tmpl w:val="01A42C48"/><w:lvl w:ilvl="0" w:tplc="14EAC624"><w:start w:val="1"/><w:numFmt w:val="decimal"/><w:lvlText w:val="%1."/><w:lvlJc w:val="left"/><w:pPr><w:ind w:left="861" w:hanging="500"/><w:jc w:val="left"/></w:pPr><w:rPr><w:rFonts w:ascii="Times New Roman" w:eastAsia="Times New Roman" w:hAnsi="Times New Roman" w:cs="Times New Roman" w:hint="default"/><w:b w:val="0"/><w:bCs w:val="0"/><w:i w:val="0"/><w:iCs w:val="0"/><w:spacing w:val="0"/><w:w w:val="101"/><w:sz w:val="45"/><w:szCs w:val="45"/><w:lang w:val="en-US" w:eastAsia="en-US" w:bidi="ar-SA"/></w:rPr></w:lvl><w:lvl w:ilvl="1" w:tplc="D318F3C6"><w:numFmt w:val="bullet"/><w:lvlText w:val="◦"/><w:lvlJc w:val="left"/><w:pPr><w:ind w:left="1581" w:hanging="500"/></w:pPr><w:rPr><w:rFonts w:ascii="Times New Roman" w:eastAsia="Times New Roman" w:hAnsi="Times New Roman" w:cs="Times New Roman" w:hint="default"/><w:b w:val="0"/><w:bCs w:val="0"/><w:i w:val="0"/><w:iCs w:val="0"/><w:spacing w:val="0"/><w:w w:val="101"/><w:position w:val="-1"/><w:sz w:val="45"/><w:szCs w:val="45"/><w:lang w:val="en-US" w:eastAsia="en-US" w:bidi="ar-SA"/></w:rPr></w:lvl><w:lvl w:ilvl="2" w:tplc="B50ACA7C"><w:numFmt w:val="bullet"/><w:lvlText w:val="•"/><w:lvlJc w:val="left"/><w:pPr><w:ind w:left="2491" w:hanging="500"/></w:pPr><w:rPr><w:rFonts w:hint="default"/><w:lang w:val="en-US" w:eastAsia="en-US" w:bidi="ar-SA"/></w:rPr></w:lvl><w:lvl w:ilvl="3" w:tplc="99DAD602"><w:numFmt w:val="bullet"/><w:lvlText w:val="•"/><w:lvlJc w:val="left"/><w:pPr><w:ind w:left="3402" w:hanging="500"/></w:pPr><w:rPr><w:rFonts w:hint="default"/><w:lang w:val="en-US" w:eastAsia="en-US" w:bidi="ar-SA"/></w:rPr></w:lvl><w:lvl w:ilvl="4" w:tplc="A74E0F2A"><w:numFmt w:val="bullet"/><w:lvlText w:val="•"/><w:lvlJc w:val="left"/><w:pPr><w:ind w:left="4313" w:hanging="500"/></w:pPr><w:rPr><w:rFonts w:hint="default"/><w:lang w:val="en-US" w:eastAsia="en-US" w:bidi="ar-SA"/></w:rPr></w:lvl><w:lvl w:ilvl="5" w:tplc="4358DB3E"><w:numFmt w:val="bullet"/><w:lvlText w:val="•"/><w:lvlJc w:val="left"/><w:pPr><w:ind w:left="5224" w:hanging="500"/></w:pPr><w:rPr><w:rFonts w:hint="default"/><w:lang w:val="en-US" w:eastAsia="en-US" w:bidi="ar-SA"/></w:rPr></w:lvl><w:lvl w:ilvl="6" w:tplc="959895A0"><w:numFmt w:val="bullet"/><w:lvlText w:val="•"/><w:lvlJc w:val="left"/><w:pPr><w:ind w:left="6135" w:hanging="500"/></w:pPr><w:rPr><w:rFonts w:hint="default"/><w:lang w:val="en-US" w:eastAsia="en-US" w:bidi="ar-SA"/></w:rPr></w:lvl><w:lvl w:ilvl="7" w:tplc="990E234A"><w:numFmt w:val="bullet"/><w:lvlText w:val="•"/><w:lvlJc w:val="left"/><w:pPr><w:ind w:left="7047" w:hanging="500"/></w:pPr><w:rPr><w:rFonts w:hint="default"/><w:lang w:val="en-US" w:eastAsia="en-US" w:bidi="ar-SA"/></w:rPr></w:lvl><w:lvl w:ilvl="8" w:tplc="2BACF06A"><w:numFmt w:val="bullet"/><w:lvlText w:val="•"/><w:lvlJc w:val="left"/><w:pPr><w:ind w:left="7958" w:hanging="500"/></w:pPr><w:rPr><w:rFonts w:hint="default"/><w:lang w:val="en-US" w:eastAsia="en-US" w:bidi="ar-SA"/></w:rPr></w:lvl></w:abstractNum><w:abstractNum w:abstractNumId="2" w15:restartNumberingAfterBreak="0"><w:nsid w:val="54EA6982"/><w:multiLevelType w:val="hybridMultilevel"/><w:tmpl w:val="F266F820"/><w:lvl w:ilvl="0" w:tplc="A358DAAC"><w:start w:val="1"/><w:numFmt w:val="decimal"/><w:lvlText w:val="%1)"/><w:lvlJc w:val="left"/><w:pPr><w:ind w:left="661" w:hanging="520"/><w:jc w:val="left"/></w:pPr><w:rPr><w:rFonts w:ascii="Times New Roman" w:eastAsia="Times New Roman" w:hAnsi="Times New Roman" w:cs="Times New Roman" w:hint="default"/><w:b/><w:bCs/><w:i w:val="0"/><w:iCs w:val="0"/><w:spacing w:val="0"/><w:w w:val="100"/><w:sz w:val="48"/><w:szCs w:val="48"/><w:lang w:val="en-US" w:eastAsia="en-US" w:bidi="ar-SA"/></w:rPr></w:lvl><w:lvl w:ilvl="1" w:tplc="93D6F0F8"><w:numFmt w:val="bullet"/><w:lvlText w:val="•"/><w:lvlJc w:val="left"/><w:pPr><w:ind w:left="861" w:hanging="500"/></w:pPr><w:rPr><w:rFonts w:ascii="Times New Roman" w:eastAsia="Times New Roman" w:hAnsi="Times New Roman" w:cs="Times New Roman" w:hint="default"/><w:b w:val="0"/><w:bCs w:val="0"/><w:i w:val="0"/><w:iCs w:val="0"/><w:spacing w:val="0"/><w:w w:val="100"/><w:sz w:val="38"/><w:szCs w:val="38"/><w:lang w:val="en-US" w:eastAsia="en-US" w:bidi="ar-SA"/></w:rPr></w:lvl><w:lvl w:ilvl="2" w:tplc="1E3C6DC4"><w:numFmt w:val="bullet"/><w:lvlText w:val="◦"/><w:lvlJc w:val="left"/><w:pPr><w:ind w:left="1581" w:hanging="500"/></w:pPr><w:rPr><w:rFonts w:ascii="Times New Roman" w:eastAsia="Times New Roman" w:hAnsi="Times New Roman" w:cs="Times New Roman" w:hint="default"/><w:b w:val="0"/><w:bCs w:val="0"/><w:i w:val="0"/><w:iCs w:val="0"/><w:spacing w:val="0"/><w:w w:val="100"/><w:position w:val="-1"/><w:sz w:val="38"/><w:szCs w:val="38"/><w:lang w:val="en-US" w:eastAsia="en-US" w:bidi="ar-SA"/></w:rPr></w:lvl><w:lvl w:ilvl="3" w:tplc="57085B3A"><w:numFmt w:val="bullet"/><w:lvlText w:val="•"/><w:lvlJc w:val="left"/><w:pPr><w:ind w:left="2605" w:hanging="500"/></w:pPr><w:rPr><w:rFonts w:hint="default"/><w:lang w:val="en-US" w:eastAsia="en-US" w:bidi="ar-SA"/></w:rPr></w:lvl><w:lvl w:ilvl="4" w:tplc="28FA44E6"><w:numFmt w:val="bullet"/><w:lvlText w:val="•"/><w:lvlJc w:val="left"/><w:pPr><w:ind w:left="3630" w:hanging="500"/></w:pPr><w:rPr><w:rFonts w:hint="default"/><w:lang w:val="en-US" w:eastAsia="en-US" w:bidi="ar-SA"/></w:rPr></w:lvl><w:lvl w:ilvl="5" w:tplc="868C0EB8"><w:numFmt w:val="bullet"/><w:lvlText w:val="•"/><w:lvlJc w:val="left"/><w:pPr><w:ind w:left="4655" w:hanging="500"/></w:pPr><w:rPr><w:rFonts w:hint="default"/><w:lang w:val="en-US" w:eastAsia="en-US" w:bidi="ar-SA"/></w:rPr></w:lvl><w:lvl w:ilvl="6" w:tplc="0658DE42"><w:numFmt w:val="bullet"/><w:lvlText w:val="•"/><w:lvlJc w:val="left"/><w:pPr><w:ind w:left="5680" w:hanging="500"/></w:pPr><w:rPr><w:rFonts w:hint="default"/><w:lang w:val="en-US" w:eastAsia="en-US" w:bidi="ar-SA"/></w:rPr></w:lvl><w:lvl w:ilvl="7" w:tplc="3CB435A0"><w:numFmt w:val="bullet"/><w:lvlText w:val="•"/><w:lvlJc w:val="left"/><w:pPr><w:ind w:left="6705" w:hanging="500"/></w:pPr><w:rPr><w:rFonts w:hint="default"/><w:lang w:val="en-US" w:eastAsia="en-US" w:bidi="ar-SA"/></w:rPr></w:lvl><w:lvl w:ilvl="8" w:tplc="B9905424"><w:numFmt w:val="bullet"/><w:lvlText w:val="•"/><w:lvlJc w:val="left"/><w:pPr><w:ind w:left="7730" w:hanging="500"/></w:pPr><w:rPr><w:rFonts w:hint="default"/><w:lang w:val="en-US" w:eastAsia="en-US" w:bidi="ar-SA"/></w:rPr></w:lvl></w:abstractNum><w:num w:numId="1" w16cid:durableId="1626734739"><w:abstractNumId w:val="0"/></w:num><w:num w:numId="2" w16cid:durableId="1550341092"><w:abstractNumId w:val="1"/></w:num><w:num w:numId="3" w16cid:durableId="2057968567"><w:abstractNumId w:val="2"/></w:num></w:numbering>